fleettools/__init__.py
fleettools/admin.py
fleettools/apps.py
fleettools/auth_hooks.py
fleettools/forms.py
fleettools/models.py
fleettools/provider.py
fleettools/tasks.py
fleettools/urls.py
fleettools/utils.py
fleettools/views.py
fleettools/migrations/0001_initial.py
fleettools/migrations/__init__.py
fleettools/static/fleettools/js/nested-checkboxes.js
fleettools/templates/fleettools/base.html
fleettools/templates/fleettools/fleetmover.html
aa_fleettools-0.1.0.dist-info/LICENSE
aa_fleettools-0.1.0.dist-info/WHEEL
aa_fleettools-0.1.0.dist-info/METADATA
aa_fleettools-0.1.0.dist-info/RECORD
