Metadata-Version: 2.1
Name: aa-fleettools
Version: 0.1.0
Summary: Fleet Tools for AllianceAuth
Keywords: allianceauth,eveonline,aa-fleettools,fleettools
Author-email: Matteo Ghia <matteo.ghia@yahoo.it>
Requires-Python: ~=3.8
Classifier: Environment :: Web Environment
Classifier: Framework :: Django
Classifier: Framework :: Django :: 4
Classifier: Framework :: Django :: 4.0
Classifier: Framework :: Django :: 4.1
Classifier: Framework :: Django :: 4.2
Classifier: Operating System :: POSIX :: Linux
Classifier: Development Status :: 3 - Alpha
Classifier: Intended Audience :: Developers
Classifier: License :: OSI Approved :: GNU General Public License v3 (GPLv3)
Classifier: Natural Language :: English
Classifier: Programming Language :: Python :: 3
Classifier: Programming Language :: Python :: 3.8
Classifier: Programming Language :: Python :: 3.9
Classifier: Programming Language :: Python :: 3.10
Classifier: Programming Language :: Python :: 3.11
Classifier: Programming Language :: Python :: 3.12
Classifier: Topic :: Internet :: WWW/HTTP
Classifier: Topic :: Internet :: WWW/HTTP :: Dynamic Content
Requires-Dist: allianceauth~=4.0
Project-URL: Changelog, https://github.com/Maestro-Zacht/aa-fleettools/releases
Project-URL: Homepage, https://github.com/Maestro-Zacht/aa-fleettools
Project-URL: Source, https://github.com/Maestro-Zacht/aa-fleettools
Project-URL: Tracker, https://github.com/Maestro-Zacht/aa-fleettools/issues
